phoenix/__init__.py
phoenix/client.py
phoenix/events.py
phoenix/market.py
phoenix/market_metadata.py
phoenix/order_subscribe_response.py
phoenix/program_id.py
phoenix/instructions/__init__.py
phoenix/instructions/cancel_all_orders.py
phoenix/instructions/cancel_all_orders_with_free_funds.py
phoenix/instructions/cancel_multiple_orders_by_id.py
phoenix/instructions/cancel_multiple_orders_by_id_with_free_funds.py
phoenix/instructions/cancel_up_to.py
phoenix/instructions/cancel_up_to_with_free_funds.py
phoenix/instructions/deposit_funds.py
phoenix/instructions/place_limit_order.py
phoenix/instructions/place_limit_order_with_free_funds.py
phoenix/instructions/reduce_order.py
phoenix/instructions/reduce_order_with_free_funds.py
phoenix/instructions/swap.py
phoenix/instructions/swap_with_free_funds.py
phoenix/instructions/withdraw_funds.py
phoenix/types/__init__.py
phoenix/types/audit_log_header.py
phoenix/types/cancel_multiple_orders_by_id_params.py
phoenix/types/cancel_order_params.py
phoenix/types/cancel_up_to_params.py
phoenix/types/condensed_order.py
phoenix/types/deposit_params.py
phoenix/types/evict_event.py
phoenix/types/expired_order_event.py
phoenix/types/failed_multiple_limit_order_behavior.py
phoenix/types/fee_event.py
phoenix/types/fifo_order_id.py
phoenix/types/fifo_resting_order.py
phoenix/types/fill_event.py
phoenix/types/fill_summary_event.py
phoenix/types/market_header.py
phoenix/types/market_size_params.py
phoenix/types/market_status.py
phoenix/types/multiple_order_packet.py
phoenix/types/order_packet.py
phoenix/types/phoenix_market_event.py
phoenix/types/place_event.py
phoenix/types/reduce_event.py
phoenix/types/reduce_order_params.py
phoenix/types/seat.py
phoenix/types/seat_approval_status.py
phoenix/types/self_trade_behavior.py
phoenix/types/side.py
phoenix/types/time_in_force_event.py
phoenix/types/token_params.py
phoenix/types/trader_state.py
phoenix/types/withdraw_params.py
phoenix_trade-0.1.9.dist-info/LICENSE
phoenix_trade-0.1.9.dist-info/METADATA
phoenix_trade-0.1.9.dist-info/WHEEL
phoenix_trade-0.1.9.dist-info/top_level.txt
phoenix_trade-0.1.9.dist-info/RECORD
