Metadata-Version: 2.1
Name: phoenix-trade
Version: 0.1.9
Summary: A Python library for interacting with Phoenix, a limit order book spot exchange on the Solana blockchain.
Author-email: Ellipsis Labs <contributors@ellipsislabs.xyz>
Project-URL: Homepage, https://github.com/Ellipsis-Labs/phoenixpy/
Classifier: Programming Language :: Python :: 3
Classifier: License :: OSI Approved :: MIT License
Classifier: Operating System :: OS Independent
Requires-Python: >=3.7
License-File: LICENSE
